bennett/__init__.py
bennett/chat.py
bennett-0.1.2.dist-info/METADATA
bennett-0.1.2.dist-info/WHEEL
bennett-0.1.2.dist-info/top_level.txt
bennett-0.1.2.dist-info/RECORD
