Metadata-Version: 2.1
Name: bennett
Version: 0.1.2
Summary: A simple wrapper to query Groq's LLaMA-3 models using streaming
Author: Harrison Bennett J
Author-email: harrisonbennett30@gmail.com
Requires-Python: >=3.7
Requires-Dist: groq
Requires-Dist: python-dotenv
